FluidPyPLC/GUI.py
FluidPyPLC/__init__.py
FluidPyPLC/data.py
FluidPyPLC/diagrams.py
FluidPyPLC/f.py
FluidPyPLC/get_sequence.py
FluidPyPLC/plc.py
FluidPyPLC/set_groups.py
FluidPyPLC/set_switches.py
FluidPyPLC/LadderLogic/__init__.py
FluidPyPLC/LadderLogic/ld.py
FluidPyPLC/resources/config.json
FluidPyPLC-0.3.501.dist-info/LICENSE
FluidPyPLC-0.3.501.dist-info/METADATA
FluidPyPLC-0.3.501.dist-info/WHEEL
FluidPyPLC-0.3.501.dist-info/entry_points.txt
FluidPyPLC-0.3.501.dist-info/top_level.txt
FluidPyPLC-0.3.501.dist-info/RECORD
