Metadata-Version: 2.1
Name: FluidPyPLC
Version: 0.3.501
Summary: FluidSim Circuits Analyzer & PLC ST Code Generator
Home-page: https://github.com/MrLostInTheInternet/FluidPyPLC
Author: MrLostInTheInternet (Eugen Iofciu Vasile)
Author-email: <eugen.iofciuvasile@hotmail.com>
License: GPLv3
Keywords: python,plc,fluidsim,structured text,plc python,codesys,circuits,pneumatics,oleodynamics,plc programming
Classifier: Development Status :: 1 - Planning
Classifier: Intended Audience :: Developers
Classifier: Programming Language :: Python :: 3
Classifier: Operating System :: Unix
Classifier: Operating System :: MacOS :: MacOS X
Classifier: Operating System :: Microsoft :: Windows
License-File: LICENSE
Requires-Dist: PySimpleGUI
Requires-Dist: matplotlib
Requires-Dist: tk
Requires-Dist: ttkbootstrap
Requires-Dist: pillow
